PyHyperChat/__init__.py
PyHyperChat/api.py
PyHyperChat/chat.py
PyHyperChat-0.1.9.dist-info/METADATA
PyHyperChat-0.1.9.dist-info/WHEEL
PyHyperChat-0.1.9.dist-info/top_level.txt
PyHyperChat-0.1.9.dist-info/RECORD
