Metadata-Version: 2.1
Name: PyHyperChat
Version: 0.1.9
Summary: HyperChat Bot Library
Author: ConnorDev
License: MIT
Platform: UNKNOWN
